pyganja/GanjaScene.py
pyganja/__init__.py
pyganja/_version.py
pyganja/cefwindow.py
pyganja/color.py
pyganja/g3c.py
pyganja/script_api.py
pyganja/static/ganja.js/ganja.js
pyganja-0.0.15.dist-info/LICENSE
pyganja-0.0.15.dist-info/METADATA
pyganja-0.0.15.dist-info/WHEEL
pyganja-0.0.15.dist-info/top_level.txt
pyganja-0.0.15.dist-info/RECORD
