Metadata-Version: 2.1
Name: pyganja
Version: 0.0.15
Summary: Python interface to ganja.js
Home-page: https://github.com/hugohadfield/pyganja
Author: Hugo Hadfield
Author-email: hadfield.hugo@gmail.com
License: MIT
Platform: UNKNOWN
Requires-Dist: IPython
